media_similarity/__init__.py
media_similarity/adaptive_threshold.py
media_similarity/exceptions.py
media_similarity/idf_context.py
media_similarity/media_pair.py
media_similarity/media_similarity_service.py
media_similarity/repositories.py
media_similarity/telemetry.py
media_similarity/entrypoints/__init__.py
media_similarity/entrypoints/cli.py
media_similarity/entrypoints/server.py
media_similarity/entrypoints/tracer.py
media_similarity-0.9.0.dist-info/METADATA
media_similarity-0.9.0.dist-info/WHEEL
media_similarity-0.9.0.dist-info/entry_points.txt
media_similarity-0.9.0.dist-info/top_level.txt
media_similarity-0.9.0.dist-info/RECORD
