Metadata-Version: 2.4
Name: media-similarity
Version: 0.9.0
Summary: Groups similar media into clusters
Author-email: Andrei Markin <amarkin@google.com>, Sergei Dorogin <segy@google.com>, "Google Inc. (gTech gPS CSE team)" <no-reply@google.com>
Classifier: Development Status :: 4 - Beta
Classifier: Programming Language :: Python
Requires-Python: >=3.10
Requires-Dist: media-tagging>=2.2.1
Requires-Dist: igraph
Requires-Dist: typer
Requires-Dist: opentelemetry-api
Requires-Dist: opentelemetry-sdk
Requires-Dist: opentelemetry-exporter-otlp
Provides-Extra: server
Requires-Dist: media-tagging[server]; extra == "server"
Provides-Extra: all
Requires-Dist: media-similarity[server]; extra == "all"
